README.md
setup.py
instasteeem.egg-info/PKG-INFO
instasteeem.egg-info/SOURCES.txt
instasteeem.egg-info/dependency_links.txt
instasteeem.egg-info/entry_points.txt
instasteeem.egg-info/requires.txt
instasteeem.egg-info/top_level.txt
instasteem/__init__.py
instasteem/cli.py
instasteem/parser.py
instasteem/post_template.py
instasteem/sync.py