Metadata-Version: 1.0
Name: instasteeem
Version: 0.0.1
Summary: A CLI app/library to sync your Instagram posts to STEEM
Home-page: https://github.com/emre/instasteem
Author: Emre Yilmaz
Author-email: mail@emreyilmaz.me
License: MIT
Platform: UNKNOWN
